[
  {"name":"삼성전자우","ticker":"005935","exchange":"KS","type":"stock","market":"KR"},
  {"name":"현대차우","ticker":"005385","exchange":"KS","type":"stock","market":"KR"},
  {"name":"현대차2우B","ticker":"005387","exchange":"KS","type":"stock","market":"KR"},
  {"name":"DL이앤씨우","ticker":"000215","exchange":"KS","type":"stock","market":"KR"},
  {"name":"LG화학우","ticker":"051915","exchange":"KS","type":"stock","market":"KR"},
  {"name":"한화우","ticker":"000885","exchange":"KS","type":"stock","market":"KR"},
  {"name":"삼성생명우","ticker":"032835","exchange":"KS","type":"stock","market":"KR"},
  {"name":"삼성전기우","ticker":"009155","exchange":"KS","type":"stock","market":"KR"},
  {"name":"SK이노베이션우","ticker":"096775","exchange":"KS","type":"stock","market":"KR"},
  {"name":"메리츠금융지주우","ticker":"138041","exchange":"KS","type":"stock","market":"KR"},
  {"name":"삼성SDI우","ticker":"006405","exchange":"KS","type":"stock","market":"KR"},
  {"name":"하이트진로우","ticker":"000070","exchange":"KS","type":"stock","market":"KR"},
  {"name":"현대건설우","ticker":"000725","exchange":"KS","type":"stock","market":"KR"},
  {"name":"LG우","ticker":"003555","exchange":"KS","type":"stock","market":"KR"},
  {"name":"대웅제약우","ticker":"003547","exchange":"KS","type":"stock","market":"KR"},
  {"name":"현대해상우","ticker":"001465","exchange":"KS","type":"stock","market":"KR"},
  {"name":"이수화학우","ticker":"007575","exchange":"KS","type":"stock","market":"KR"},
  {"name":"삼양사우","ticker":"004545","exchange":"KS","type":"stock","market":"KR"},
  {"name":"GS우","ticker":"078935","exchange":"KS","type":"stock","market":"KR"},
  {"name":"효성우","ticker":"004835","exchange":"KS","type":"stock","market":"KR"},
  {"name":"SK케미칼우","ticker":"003605","exchange":"KS","type":"stock","market":"KR"},
  {"name":"두산우","ticker":"000155","exchange":"KS","type":"stock","market":"KR"},
  {"name":"SK우","ticker":"001515","exchange":"KS","type":"stock","market":"KR"},
  {"name":"KT&G","ticker":"033780","exchange":"KS","type":"stock","market":"KR"},
  {"name":"삼성전자","ticker":"005930","exchange":"KS","type":"stock","market":"KR"},
  {"name":"SK하이닉스","ticker":"000660","exchange":"KS","type":"stock","market":"KR"},
  {"name":"삼성전기","ticker":"009150","exchange":"KS","type":"stock","market":"KR"},
  {"name":"LG이노텍","ticker":"011070","exchange":"KS","type":"stock","market":"KR"},
  {"name":"LG전자","ticker":"066570","exchange":"KS","type":"stock","market":"KR"},
  {"name":"삼성중공업","ticker":"010140","exchange":"KS","type":"stock","market":"KR"},
  {"name":"한미반도체","ticker":"042700","exchange":"KQ","type":"stock","market":"KR"},
  {"name":"DB하이텍","ticker":"000990","exchange":"KS","type":"stock","market":"KR"},
  {"name":"솔브레인홀딩스","ticker":"336370","exchange":"KQ","type":"stock","market":"KR"},
  {"name":"원익IPS","ticker":"240810","exchange":"KQ","type":"stock","market":"KR"},
  {"name":"이오테크닉스","ticker":"089890","exchange":"KQ","type":"stock","market":"KR"},
  {"name":"테스","ticker":"131970","exchange":"KQ","type":"stock","market":"KR"},
  {"name":"유진테크","ticker":"084370","exchange":"KQ","type":"stock","market":"KR"},
  {"name":"덕산네오룩스","ticker":"213420","exchange":"KQ","type":"stock","market":"KR"},
  {"name":"원익머트리얼즈","ticker":"122830","exchange":"KQ","type":"stock","market":"KR"},
  {"name":"SFA반도체","ticker":"036540","exchange":"KQ","type":"stock","market":"KR"},
  {"name":"오스코텍","ticker":"048260","exchange":"KQ","type":"stock","market":"KR"},
  {"name":"KB금융","ticker":"105560","exchange":"KS","type":"stock","market":"KR"},
  {"name":"신한지주","ticker":"055550","exchange":"KS","type":"stock","market":"KR"},
  {"name":"하나금융지주","ticker":"086790","exchange":"KS","type":"stock","market":"KR"},
  {"name":"우리금융지주","ticker":"316140","exchange":"KS","type":"stock","market":"KR"},
  {"name":"기업은행","ticker":"024110","exchange":"KS","type":"stock","market":"KR"},
  {"name":"BNK금융지주","ticker":"138930","exchange":"KS","type":"stock","market":"KR"},
  {"name":"DGB금융지주","ticker":"139130","exchange":"KS","type":"stock","market":"KR"},
  {"name":"JB금융지주","ticker":"175330","exchange":"KS","type":"stock","market":"KR"},
  {"name":"메리츠금융지주","ticker":"138040","exchange":"KS","type":"stock","market":"KR"},
  {"name":"카카오뱅크","ticker":"323410","exchange":"KS","type":"stock","market":"KR"},
  {"name":"카카오페이","ticker":"377300","exchange":"KS","type":"stock","market":"KR"},
  {"name":"키움증권","ticker":"039490","exchange":"KS","type":"stock","market":"KR"},
  {"name":"미래에셋증권","ticker":"037620","exchange":"KS","type":"stock","market":"KR"},
  {"name":"삼성증권","ticker":"016360","exchange":"KS","type":"stock","market":"KR"},
  {"name":"NH투자증권","ticker":"005940","exchange":"KS","type":"stock","market":"KR"},
  {"name":"유안타증권","ticker":"003470","exchange":"KS","type":"stock","market":"KR"},
  {"name":"이베스트투자증권","ticker":"078020","exchange":"KS","type":"stock","market":"KR"},
  {"name":"교보증권","ticker":"030610","exchange":"KS","type":"stock","market":"KR"},
  {"name":"대신증권","ticker":"003540","exchange":"KS","type":"stock","market":"KR"},
  {"name":"현대차증권","ticker":"001500","exchange":"KS","type":"stock","market":"KR"},
  {"name":"한화투자증권","ticker":"039670","exchange":"KS","type":"stock","market":"KR"},
  {"name":"삼성생명","ticker":"032830","exchange":"KS","type":"stock","market":"KR"},
  {"name":"한화생명","ticker":"088350","exchange":"KS","type":"stock","market":"KR"},
  {"name":"DB손해보험","ticker":"005830","exchange":"KS","type":"stock","market":"KR"},
  {"name":"삼성화재","ticker":"000810","exchange":"KS","type":"stock","market":"KR"},
  {"name":"현대해상","ticker":"001450","exchange":"KS","type":"stock","market":"KR"},
  {"name":"메리츠화재","ticker":"000060","exchange":"KS","type":"stock","market":"KR"},
  {"name":"비엔케이캐피탈","ticker":"082920","exchange":"KS","type":"stock","market":"KR"},
  {"name":"SK텔레콤","ticker":"017670","exchange":"KS","type":"stock","market":"KR"},
  {"name":"KT","ticker":"030200","exchange":"KS","type":"stock","market":"KR"},
  {"name":"LG유플러스","ticker":"032640","exchange":"KS","type":"stock","market":"KR"},
  {"name":"현대차","ticker":"005380","exchange":"KS","type":"stock","market":"KR"},
  {"name":"기아","ticker":"000270","exchange":"KS","type":"stock","market":"KR"},
  {"name":"현대모비스","ticker":"012330","exchange":"KS","type":"stock","market":"KR"},
  {"name":"한국타이어앤테크놀로지","ticker":"161390","exchange":"KS","type":"stock","market":"KR"},
  {"name":"넥센타이어","ticker":"002390","exchange":"KS","type":"stock","market":"KR"},
  {"name":"현대제철","ticker":"004020","exchange":"KS","type":"stock","market":"KR"},
  {"name":"한온시스템","ticker":"018880","exchange":"KS","type":"stock","market":"KR"},
  {"name":"현대미포조선","ticker":"010620","exchange":"KS","type":"stock","market":"KR"},
  {"name":"현대엘리베이터","ticker":"007340","exchange":"KS","type":"stock","market":"KR"},
  {"name":"일양약품","ticker":"007570","exchange":"KS","type":"stock","market":"KR"},
  {"name":"네이버","ticker":"035420","exchange":"KS","type":"stock","market":"KR"},
  {"name":"카카오","ticker":"035720","exchange":"KS","type":"stock","market":"KR"},
  {"name":"크래프톤","ticker":"259960","exchange":"KS","type":"stock","market":"KR"},
  {"name":"엔씨소프트","ticker":"036570","exchange":"KS","type":"stock","market":"KR"},
  {"name":"넷마블","ticker":"251270","exchange":"KS","type":"stock","market":"KR"},
  {"name":"펄어비스","ticker":"263750","exchange":"KS","type":"stock","market":"KR"},
  {"name":"네오위즈","ticker":"095660","exchange":"KQ","type":"stock","market":"KR"},
  {"name":"컴투스","ticker":"078340","exchange":"KQ","type":"stock","market":"KR"},
  {"name":"넥슨게임즈","ticker":"225570","exchange":"KQ","type":"stock","market":"KR"},
  {"name":"더블유게임즈","ticker":"192080","exchange":"KQ","type":"stock","market":"KR"},
  {"name":"메가스터디","ticker":"041920","exchange":"KQ","type":"stock","market":"KR"},
  {"name":"다날","ticker":"064260","exchange":"KQ","type":"stock","market":"KR"},
  {"name":"S-Oil","ticker":"010950","exchange":"KS","type":"stock","market":"KR"},
  {"name":"SK이노베이션","ticker":"096770","exchange":"KS","type":"stock","market":"KR"},
  {"name":"GS","ticker":"078930","exchange":"KS","type":"stock","market":"KR"},
  {"name":"한국전력","ticker":"015760","exchange":"KS","type":"stock","market":"KR"},
  {"name":"한국가스공사","ticker":"036460","exchange":"KS","type":"stock","market":"KR"},
  {"name":"맥쿼리인프라","ticker":"088980","exchange":"KS","type":"reit","market":"KR"},
  {"name":"대성에너지","ticker":"117580","exchange":"KS","type":"stock","market":"KR"},
  {"name":"인천도시가스","ticker":"034590","exchange":"KS","type":"stock","market":"KR"},
  {"name":"한국가스기술공사","ticker":"071050","exchange":"KS","type":"stock","market":"KR"},
  {"name":"포스코홀딩스","ticker":"005490","exchange":"KS","type":"stock","market":"KR"},
  {"name":"고려아연","ticker":"010130","exchange":"KS","type":"stock","market":"KR"},
  {"name":"영풍","ticker":"000670","exchange":"KS","type":"stock","market":"KR"},
  {"name":"KCC","ticker":"002380","exchange":"KS","type":"stock","market":"KR"},
  {"name":"금호석유","ticker":"073240","exchange":"KS","type":"stock","market":"KR"},
  {"name":"LG화학","ticker":"051910","exchange":"KS","type":"stock","market":"KR"},
  {"name":"삼성SDI","ticker":"006400","exchange":"KS","type":"stock","market":"KR"},
  {"name":"롯데케미칼","ticker":"011170","exchange":"KS","type":"stock","market":"KR"},
  {"name":"포스코인터내셔널","ticker":"047050","exchange":"KS","type":"stock","market":"KR"},
  {"name":"동국제강","ticker":"001230","exchange":"KS","type":"stock","market":"KR"},
  {"name":"한화솔루션","ticker":"009420","exchange":"KS","type":"stock","market":"KR"},
  {"name":"SKC","ticker":"011790","exchange":"KS","type":"stock","market":"KR"},
  {"name":"코오롱인더","ticker":"120110","exchange":"KS","type":"stock","market":"KR"},
  {"name":"한솔케미칼","ticker":"014680","exchange":"KS","type":"stock","market":"KR"},
  {"name":"효성화학","ticker":"298000","exchange":"KS","type":"stock","market":"KR"},
  {"name":"OCI홀딩스","ticker":"010060","exchange":"KS","type":"stock","market":"KR"},
  {"name":"롯데정밀화학","ticker":"004000","exchange":"KS","type":"stock","market":"KR"},
  {"name":"넥스틸","ticker":"002350","exchange":"KS","type":"stock","market":"KR"},
  {"name":"세아제강지주","ticker":"017890","exchange":"KS","type":"stock","market":"KR"},
  {"name":"세아베스틸지주","ticker":"306200","exchange":"KS","type":"stock","market":"KR"},
  {"name":"동일방직","ticker":"014830","exchange":"KS","type":"stock","market":"KR"},
  {"name":"DN오토모티브","ticker":"024090","exchange":"KS","type":"stock","market":"KR"},
  {"name":"테이팩스","ticker":"004985","exchange":"KS","type":"stock","market":"KR"},
  {"name":"SK","ticker":"034730","exchange":"KS","type":"stock","market":"KR"},
  {"name":"LG","ticker":"003550","exchange":"KS","type":"stock","market":"KR"},
  {"name":"두산","ticker":"000150","exchange":"KS","type":"stock","market":"KR"},
  {"name":"한화","ticker":"000880","exchange":"KS","type":"stock","market":"KR"},
  {"name":"CJ","ticker":"001040","exchange":"KS","type":"stock","market":"KR"},
  {"name":"LS","ticker":"006260","exchange":"KS","type":"stock","market":"KR"},
  {"name":"삼성물산","ticker":"028260","exchange":"KS","type":"stock","market":"KR"},
  {"name":"HD현대","ticker":"267250","exchange":"KS","type":"stock","market":"KR"},
  {"name":"효성","ticker":"004800","exchange":"KS","type":"stock","market":"KR"},
  {"name":"유한양행","ticker":"000100","exchange":"KS","type":"stock","market":"KR"},
  {"name":"동성제약","ticker":"002210","exchange":"KS","type":"stock","market":"KR"},
  {"name":"LX홀딩스","ticker":"001120","exchange":"KS","type":"stock","market":"KR"},
  {"name":"LIG넥스원","ticker":"079550","exchange":"KS","type":"stock","market":"KR"},
  {"name":"하이트진로홀딩스","ticker":"071840","exchange":"KS","type":"stock","market":"KR"},
  {"name":"삼성바이오로직스","ticker":"207940","exchange":"KS","type":"stock","market":"KR"},
  {"name":"셀트리온","ticker":"068270","exchange":"KS","type":"stock","market":"KR"},
  {"name":"한미약품","ticker":"128940","exchange":"KS","type":"stock","market":"KR"},
  {"name":"종근당","ticker":"185750","exchange":"KS","type":"stock","market":"KR"},
  {"name":"대웅","ticker":"003090","exchange":"KS","type":"stock","market":"KR"},
  {"name":"대웅제약","ticker":"069620","exchange":"KS","type":"stock","market":"KR"},
  {"name":"유유제약","ticker":"000220","exchange":"KS","type":"stock","market":"KR"},
  {"name":"JW중외제약","ticker":"001060","exchange":"KS","type":"stock","market":"KR"},
  {"name":"오리엔트바이오","ticker":"002630","exchange":"KS","type":"stock","market":"KR"},
  {"name":"휴젤","ticker":"145020","exchange":"KQ","type":"stock","market":"KR"},
  {"name":"동진쎄미켐","ticker":"012800","exchange":"KS","type":"stock","market":"KR"},
  {"name":"동아에스티","ticker":"170900","exchange":"KS","type":"stock","market":"KR"},
  {"name":"동아쏘시오홀딩스","ticker":"003520","exchange":"KS","type":"stock","market":"KR"},
  {"name":"BGF리테일","ticker":"282330","exchange":"KS","type":"stock","market":"KR"},
  {"name":"GS리테일","ticker":"007070","exchange":"KS","type":"stock","market":"KR"},
  {"name":"이마트","ticker":"139480","exchange":"KS","type":"stock","market":"KR"},
  {"name":"롯데쇼핑","ticker":"023530","exchange":"KS","type":"stock","market":"KR"},
  {"name":"CJ제일제당","ticker":"097950","exchange":"KS","type":"stock","market":"KR"},
  {"name":"대상","ticker":"001680","exchange":"KS","type":"stock","market":"KR"},
  {"name":"하이트진로","ticker":"000080","exchange":"KS","type":"stock","market":"KR"},
  {"name":"신세계","ticker":"004170","exchange":"KS","type":"stock","market":"KR"},
  {"name":"현대백화점","ticker":"069960","exchange":"KS","type":"stock","market":"KR"},
  {"name":"오리온","ticker":"271560","exchange":"KS","type":"stock","market":"KR"},
  {"name":"아모레퍼시픽","ticker":"002790","exchange":"KS","type":"stock","market":"KR"},
  {"name":"LG생활건강","ticker":"051900","exchange":"KS","type":"stock","market":"KR"},
  {"name":"빙그레","ticker":"005180","exchange":"KS","type":"stock","market":"KR"},
  {"name":"남양유업","ticker":"008350","exchange":"KS","type":"stock","market":"KR"},
  {"name":"덴티움","ticker":"004830","exchange":"KS","type":"stock","market":"KR"},
  {"name":"삼양식품","ticker":"003230","exchange":"KS","type":"stock","market":"KR"},
  {"name":"SPC삼립","ticker":"005610","exchange":"KS","type":"stock","market":"KR"},
  {"name":"롯데제과","ticker":"004990","exchange":"KS","type":"stock","market":"KR"},
  {"name":"계열","ticker":"007030","exchange":"KS","type":"stock","market":"KR"},
  {"name":"HLB생명과학","ticker":"003580","exchange":"KS","type":"stock","market":"KR"},
  {"name":"SK디스커버리","ticker":"006120","exchange":"KS","type":"stock","market":"KR"},
  {"name":"현대건설","ticker":"000720","exchange":"KS","type":"stock","market":"KR"},
  {"name":"DL이앤씨","ticker":"375500","exchange":"KS","type":"stock","market":"KR"},
  {"name":"GS건설","ticker":"006360","exchange":"KS","type":"stock","market":"KR"},
  {"name":"대우건설","ticker":"047040","exchange":"KS","type":"stock","market":"KR"},
  {"name":"HDC현대산업개발","ticker":"294870","exchange":"KS","type":"stock","market":"KR"},
  {"name":"태영건설","ticker":"009410","exchange":"KS","type":"stock","market":"KR"},
  {"name":"계룡건설산업","ticker":"013580","exchange":"KS","type":"stock","market":"KR"},
  {"name":"금호건설","ticker":"002990","exchange":"KS","type":"stock","market":"KR"},
  {"name":"코오롱글로벌","ticker":"003070","exchange":"KS","type":"stock","market":"KR"},
  {"name":"한신공영","ticker":"004960","exchange":"KS","type":"stock","market":"KR"},
  {"name":"동부건설","ticker":"005960","exchange":"KS","type":"stock","market":"KR"},
  {"name":"동양건설산업","ticker":"082640","exchange":"KS","type":"stock","market":"KR"},
  {"name":"신세계건설","ticker":"034300","exchange":"KS","type":"stock","market":"KR"},
  {"name":"삼원강재","ticker":"023000","exchange":"KS","type":"stock","market":"KR"},
  {"name":"한진중공업","ticker":"097230","exchange":"KS","type":"stock","market":"KR"},
  {"name":"롯데건설","ticker":"025700","exchange":"KS","type":"stock","market":"KR"},
  {"name":"에이스침대","ticker":"003800","exchange":"KS","type":"stock","market":"KR"},
  {"name":"일신방직","ticker":"006840","exchange":"KS","type":"stock","market":"KR"},
  {"name":"DL","ticker":"000210","exchange":"KS","type":"stock","market":"KR"},
  {"name":"한국경제TV","ticker":"023760","exchange":"KS","type":"stock","market":"KR"},
  {"name":"대동기어","ticker":"008830","exchange":"KS","type":"stock","market":"KR"},
  {"name":"KCC건설","ticker":"021320","exchange":"KS","type":"stock","market":"KR"},
  {"name":"삼성제약","ticker":"012650","exchange":"KS","type":"stock","market":"KR"},
  {"name":"영보화학","ticker":"014440","exchange":"KS","type":"stock","market":"KR"},
  {"name":"이노션","ticker":"067290","exchange":"KS","type":"stock","market":"KR"},
  {"name":"한국항공우주","ticker":"047810","exchange":"KS","type":"stock","market":"KR"},
  {"name":"HD한국조선해양","ticker":"009540","exchange":"KS","type":"stock","market":"KR"},
  {"name":"한화오션","ticker":"042660","exchange":"KS","type":"stock","market":"KR"},
  {"name":"현대로템","ticker":"064350","exchange":"KS","type":"stock","market":"KR"},
  {"name":"HD현대중공업","ticker":"329180","exchange":"KS","type":"stock","market":"KR"},
  {"name":"한화에어로스페이스","ticker":"012450","exchange":"KS","type":"stock","market":"KR"},
  {"name":"두산에너빌리티","ticker":"034020","exchange":"KS","type":"stock","market":"KR"},
  {"name":"HD현대일렉트릭","ticker":"267260","exchange":"KS","type":"stock","market":"KR"},
  {"name":"HSD엔진","ticker":"082740","exchange":"KS","type":"stock","market":"KR"},
  {"name":"화신","ticker":"010690","exchange":"KS","type":"stock","market":"KR"},
  {"name":"대한항공","ticker":"003490","exchange":"KS","type":"stock","market":"KR"},
  {"name":"한진칼","ticker":"180640","exchange":"KS","type":"stock","market":"KR"},
  {"name":"진에어","ticker":"272450","exchange":"KS","type":"stock","market":"KR"},
  {"name":"제주항공","ticker":"089590","exchange":"KS","type":"stock","market":"KR"},
  {"name":"아시아나항공","ticker":"020560","exchange":"KS","type":"stock","market":"KR"},
  {"name":"HMM","ticker":"011200","exchange":"KS","type":"stock","market":"KR"},
  {"name":"팬오션","ticker":"028670","exchange":"KS","type":"stock","market":"KR"},
  {"name":"유수홀딩스","ticker":"000700","exchange":"KS","type":"stock","market":"KR"},
  {"name":"한진","ticker":"002340","exchange":"KS","type":"stock","market":"KR"},
  {"name":"티웨이항공","ticker":"004870","exchange":"KS","type":"stock","market":"KR"},
  {"name":"강원랜드","ticker":"035250","exchange":"KS","type":"stock","market":"KR"},
  {"name":"파라다이스","ticker":"034230","exchange":"KS","type":"stock","market":"KR"},
  {"name":"하이브","ticker":"352820","exchange":"KS","type":"stock","market":"KR"},
  {"name":"SM엔터테인먼트","ticker":"041510","exchange":"KQ","type":"stock","market":"KR"},
  {"name":"JYP엔터테인먼트","ticker":"035900","exchange":"KQ","type":"stock","market":"KR"},
  {"name":"YG엔터테인먼트","ticker":"122870","exchange":"KQ","type":"stock","market":"KR"},
  {"name":"YG PLUS","ticker":"036270","exchange":"KS","type":"stock","market":"KR"},
  {"name":"이수페타시스","ticker":"007660","exchange":"KQ","type":"stock","market":"KR"},
  {"name":"한전기술","ticker":"052690","exchange":"KS","type":"stock","market":"KR"},
  {"name":"스카이라이프","ticker":"053210","exchange":"KQ","type":"stock","market":"KR"},
  {"name":"제이콘텐트리","ticker":"036420","exchange":"KQ","type":"stock","market":"KR"},
  {"name":"전방","ticker":"016890","exchange":"KS","type":"stock","market":"KR"},
  {"name":"SK리츠","ticker":"395400","exchange":"KS","type":"reit","market":"KR"},
  {"name":"KB스타리츠","ticker":"432320","exchange":"KS","type":"reit","market":"KR"},
  {"name":"한화리츠","ticker":"448730","exchange":"KS","type":"reit","market":"KR"},
  {"name":"롯데리츠","ticker":"330590","exchange":"KS","type":"reit","market":"KR"},
  {"name":"신한알파리츠","ticker":"293940","exchange":"KS","type":"reit","market":"KR"},
  {"name":"디앤디플랫폼리츠","ticker":"357430","exchange":"KS","type":"reit","market":"KR"},
  {"name":"이지스밸류리츠","ticker":"334890","exchange":"KS","type":"reit","market":"KR"},
  {"name":"레인보우로보틱스","ticker":"277810","exchange":"KQ","type":"stock","market":"KR"},
  {"name":"엘엔에프","ticker":"066970","exchange":"KQ","type":"stock","market":"KR"},
  {"name":"파마리서치","ticker":"214450","exchange":"KQ","type":"stock","market":"KR"},
  {"name":"솔루엠","ticker":"248070","exchange":"KQ","type":"stock","market":"KR"},
  {"name":"리가켐바이오","ticker":"141080","exchange":"KQ","type":"stock","market":"KR"},
  {"name":"에스티팜","ticker":"237690","exchange":"KQ","type":"stock","market":"KR"},
  {"name":"이녹스첨단소재","ticker":"272290","exchange":"KQ","type":"stock","market":"KR"},
  {"name":"비에이치","ticker":"090460","exchange":"KQ","type":"stock","market":"KR"},
  {"name":"코스메카코리아","ticker":"241710","exchange":"KQ","type":"stock","market":"KR"},
  {"name":"제이앤티씨","ticker":"204270","exchange":"KQ","type":"stock","market":"KR"},
  {"name":"셀바스AI","ticker":"108860","exchange":"KQ","type":"stock","market":"KR"},
  {"name":"피에스케이홀딩스","ticker":"031980","exchange":"KQ","type":"stock","market":"KR"},
  {"name":"에이피시스템","ticker":"054080","exchange":"KQ","type":"stock","market":"KR"},
  {"name":"코스맥스","ticker":"192820","exchange":"KQ","type":"stock","market":"KR"},
  {"name":"휴온스글로벌","ticker":"084110","exchange":"KQ","type":"stock","market":"KR"},
  {"name":"JW생명과학","ticker":"234080","exchange":"KQ","type":"stock","market":"KR"},
  {"name":"씨에스윈드","ticker":"064760","exchange":"KQ","type":"stock","market":"KR"},
  {"name":"비에스한일시멘트","ticker":"145090","exchange":"KQ","type":"stock","market":"KR"},
  {"name":"SK바이오팜","ticker":"285130","exchange":"KQ","type":"stock","market":"KR"},
  {"name":"오스코텍","ticker":"039200","exchange":"KQ","type":"stock","market":"KR"},
  {"name":"스피어파워","ticker":"203690","exchange":"KQ","type":"stock","market":"KR"},
  {"name":"쏠리드","ticker":"050890","exchange":"KQ","type":"stock","market":"KR"},
  {"name":"코리아에프티","ticker":"123410","exchange":"KQ","type":"stock","market":"KR"},
  {"name":"에코프로","ticker":"086520","exchange":"KQ","type":"stock","market":"KR"},
  {"name":"에코프로비엠","ticker":"247540","exchange":"KQ","type":"stock","market":"KR"},
  {"name":"LG에너지솔루션","ticker":"373220","exchange":"KS","type":"stock","market":"KR"},
  {"name":"셀트리온헬스케어","ticker":"091990","exchange":"KQ","type":"stock","market":"KR"},
  {"name":"알테오젠","ticker":"196170","exchange":"KQ","type":"stock","market":"KR"},
  {"name":"HLB","ticker":"028300","exchange":"KQ","type":"stock","market":"KR"},
  {"name":"카카오게임즈","ticker":"293490","exchange":"KQ","type":"stock","market":"KR"},
  {"name":"리노공업","ticker":"058470","exchange":"KQ","type":"stock","market":"KR"},
  {"name":"클래시스","ticker":"214150","exchange":"KQ","type":"stock","market":"KR"},
  {"name":"HPSP","ticker":"403870","exchange":"KQ","type":"stock","market":"KR"},
  {"name":"솔브레인","ticker":"357780","exchange":"KQ","type":"stock","market":"KR"},
  {"name":"나스미디어","ticker":"036800","exchange":"KQ","type":"stock","market":"KR"},
  {"name":"위메이드","ticker":"112040","exchange":"KQ","type":"stock","market":"KR"},
  {"name":"에프에스티","ticker":"036810","exchange":"KQ","type":"stock","market":"KR"},
  {"name":"한국전자인증","ticker":"054040","exchange":"KQ","type":"stock","market":"KR"},
  {"name":"에이텍","ticker":"045660","exchange":"KQ","type":"stock","market":"KR"},
  {"name":"이엘피","ticker":"033100","exchange":"KQ","type":"stock","market":"KR"},
  {"name":"누리플렉스","ticker":"067170","exchange":"KQ","type":"stock","market":"KR"},
  {"name":"디앤씨미디어","ticker":"263720","exchange":"KQ","type":"stock","market":"KR"},
  {"name":"태광","ticker":"023160","exchange":"KQ","type":"stock","market":"KR"},
  {"name":"율호","ticker":"072770","exchange":"KQ","type":"stock","market":"KR"},
  {"name":"엘브이엠씨홀딩스","ticker":"900140","exchange":"KQ","type":"stock","market":"KR"},
  {"name":"대한유화","ticker":"006650","exchange":"KS","type":"stock","market":"KR"},
  {"name":"아이에스동서","ticker":"010780","exchange":"KS","type":"stock","market":"KR"},
  {"name":"서흥","ticker":"008490","exchange":"KQ","type":"stock","market":"KR"},
  {"name":"인바디","ticker":"041830","exchange":"KQ","type":"stock","market":"KR"},
  {"name":"더존비즈온","ticker":"012510","exchange":"KQ","type":"stock","market":"KR"},
  {"name":"파크시스템스","ticker":"140860","exchange":"KQ","type":"stock","market":"KR"},
  {"name":"원익QnC","ticker":"074600","exchange":"KQ","type":"stock","market":"KR"},
  {"name":"메디톡스","ticker":"086900","exchange":"KQ","type":"stock","market":"KR"},
  {"name":"실리콘투","ticker":"257530","exchange":"KQ","type":"stock","market":"KR"},
  {"name":"씨젠","ticker":"096530","exchange":"KQ","type":"stock","market":"KR"},
  {"name":"케어젠","ticker":"214370","exchange":"KQ","type":"stock","market":"KR"},
  {"name":"에이비엘바이오","ticker":"298380","exchange":"KQ","type":"stock","market":"KR"},
  {"name":"서울반도체","ticker":"046890","exchange":"KQ","type":"stock","market":"KR"},
  {"name":"스튜디오드래곤","ticker":"253450","exchange":"KQ","type":"stock","market":"KR"},
  {"name":"뷰노","ticker":"338220","exchange":"KQ","type":"stock","market":"KR"},
  {"name":"루닛","ticker":"328130","exchange":"KQ","type":"stock","market":"KR"},
  {"name":"일진하이솔루스","ticker":"271940","exchange":"KQ","type":"stock","market":"KR"},
  {"name":"포스코DX","ticker":"022100","exchange":"KQ","type":"stock","market":"KR"},
  {"name":"한국기업평가","ticker":"034950","exchange":"KQ","type":"stock","market":"KR"},
  {"name":"코엔텍","ticker":"029960","exchange":"KQ","type":"stock","market":"KR"},
  {"name":"엠씨넥스","ticker":"097520","exchange":"KQ","type":"stock","market":"KR"},
  {"name":"LX세미콘","ticker":"108320","exchange":"KQ","type":"stock","market":"KR"},
  {"name":"펩트론","ticker":"251970","exchange":"KQ","type":"stock","market":"KR"},

  {"name":"테라젠바이오","ticker":"199800","exchange":"KQ","type":"stock","market":"KR"},
  {"name":"하나마이크론","ticker":"149980","exchange":"KQ","type":"stock","market":"KR"},
  {"name":"다우기술","ticker":"032190","exchange":"KQ","type":"stock","market":"KR"},
  {"name":"텔코웨어","ticker":"078000","exchange":"KQ","type":"stock","market":"KR"},
  {"name":"동아엘텍","ticker":"088130","exchange":"KQ","type":"stock","market":"KR"},
  {"name":"에프엔에스테크","ticker":"083500","exchange":"KQ","type":"stock","market":"KR"},
  {"name":"미래산업","ticker":"025560","exchange":"KQ","type":"stock","market":"KR"},
  {"name":"3S","ticker":"060310","exchange":"KQ","type":"stock","market":"KR"},
  {"name":"SK네트웍스","ticker":"001740","exchange":"KS","type":"stock","market":"KR"},
  {"name":"한국단자공업","ticker":"025540","exchange":"KS","type":"stock","market":"KR"},
  {"name":"동방아그로","ticker":"007590","exchange":"KS","type":"stock","market":"KR"},
  {"name":"웰투시인베스트먼트","ticker":"016880","exchange":"KS","type":"stock","market":"KR"},
  {"name":"제일연마","ticker":"001560","exchange":"KS","type":"stock","market":"KR"},
  {"name":"영풍제지","ticker":"006740","exchange":"KS","type":"stock","market":"KR"},
  {"name":"한솔홀딩스","ticker":"004150","exchange":"KS","type":"stock","market":"KR"},
  {"name":"국제약품","ticker":"002720","exchange":"KS","type":"stock","market":"KR"},
  {"name":"웰크론","ticker":"033180","exchange":"KS","type":"stock","market":"KR"},
  {"name":"광주신세계","ticker":"009290","exchange":"KS","type":"stock","market":"KR"},
  {"name":"래몽래인","ticker":"200350","exchange":"KS","type":"stock","market":"KR"},
  {"name":"SK케미칼","ticker":"003600","exchange":"KS","type":"stock","market":"KR"},
  {"name":"쿠쿠홀딩스","ticker":"192400","exchange":"KS","type":"stock","market":"KR"},
  {"name":"쿠쿠홈시스","ticker":"284740","exchange":"KS","type":"stock","market":"KR"},
  {"name":"쌍용C&E","ticker":"003620","exchange":"KS","type":"stock","market":"KR"},
  {"name":"경동나비엔","ticker":"009450","exchange":"KS","type":"stock","market":"KR"},
  {"name":"한국투자금융지주","ticker":"002450","exchange":"KS","type":"stock","market":"KR"},
  {"name":"현대지에프홀딩스","ticker":"005440","exchange":"KS","type":"stock","market":"KR"},
  {"name":"휴스틸","ticker":"005010","exchange":"KS","type":"stock","market":"KR"},
  {"name":"한국철강","ticker":"004440","exchange":"KS","type":"stock","market":"KR"},
  {"name":"현대오토에버","ticker":"307950","exchange":"KS","type":"stock","market":"KR"},
  {"name":"STX중공업","ticker":"071970","exchange":"KS","type":"stock","market":"KR"},
  {"name":"디아이씨","ticker":"003160","exchange":"KS","type":"stock","market":"KR"},
  {"name":"화승엔터프라이즈","ticker":"013520","exchange":"KS","type":"stock","market":"KR"},
  {"name":"일진머티리얼즈","ticker":"013360","exchange":"KS","type":"stock","market":"KR"},
  {"name":"SH에너지화학","ticker":"002820","exchange":"KS","type":"stock","market":"KR"},
  {"name":"정한","ticker":"011160","exchange":"KS","type":"stock","market":"KR"},
  {"name":"한전KPS","ticker":"051600","exchange":"KS","type":"stock","market":"KR"},
  {"name":"전기초자","ticker":"016250","exchange":"KS","type":"stock","market":"KR"},
  {"name":"진양홀딩스","ticker":"100250","exchange":"KS","type":"stock","market":"KR"},
  {"name":"크라운해태홀딩스","ticker":"001300","exchange":"KS","type":"stock","market":"KR"},
  {"name":"동화기업","ticker":"025900","exchange":"KS","type":"stock","market":"KR"},
  {"name":"성신양회","ticker":"007720","exchange":"KS","type":"stock","market":"KR"},
  {"name":"정상제이엘에스","ticker":"040420","exchange":"KS","type":"stock","market":"KR"},
  {"name":"NH스팩17호","ticker":"020120","exchange":"KS","type":"stock","market":"KR"},
  {"name":"쌍용양회공업","ticker":"003410","exchange":"KS","type":"stock","market":"KR"},
  {"name":"KODEX 200","ticker":"069500","exchange":"KS","type":"etf","market":"KR"},
  {"name":"KODEX 고배당","ticker":"091160","exchange":"KS","type":"etf","market":"KR"},
  {"name":"KODEX 배당성장50","ticker":"211560","exchange":"KS","type":"etf","market":"KR"},
  {"name":"KODEX 200미국채혼합","ticker":"278530","exchange":"KS","type":"etf","market":"KR"},
  {"name":"KODEX 미국S&P500","ticker":"379800","exchange":"KS","type":"etf","market":"KR"},
  {"name":"KODEX 미국배당프리미엄액티브","ticker":"442580","exchange":"KS","type":"etf","market":"KR"},
  {"name":"KODEX 국고채10년","ticker":"308620","exchange":"KS","type":"etf","market":"KR"},
  {"name":"KODEX 단기채권PLUS","ticker":"395160","exchange":"KS","type":"etf","market":"KR"},
  {"name":"ARIRANG 고배당주","ticker":"152100","exchange":"KS","type":"etf","market":"KR"},
  {"name":"KBSTAR 비과세고배당","ticker":"226490","exchange":"KS","type":"etf","market":"KR"},
  {"name":"TIGER 200","ticker":"102110","exchange":"KS","type":"etf","market":"KR"},
  {"name":"TIGER 미국배당다우존스","ticker":"458730","exchange":"KS","type":"etf","market":"KR"},
  {"name":"TIGER 미국배당+7%프리미엄다우존스","ticker":"476550","exchange":"KS","type":"etf","market":"KR"},
  {"name":"TIGER 미국S&P500배당귀족","ticker":"404540","exchange":"KS","type":"etf","market":"KR"},
  {"name":"TIGER 리츠부동산인프라","ticker":"329200","exchange":"KS","type":"etf","market":"KR"},
  {"name":"TIGER 글로벌리츠부동산(리얼티인컴재간접)","ticker":"411060","exchange":"KS","type":"etf","market":"KR"},
  {"name":"TIGER 미국배당+3%프리미엄다우존스","ticker":"441060","exchange":"KS","type":"etf","market":"KR"},
  {"name":"TIGER 미국배당+10%프리미엄다우존스","ticker":"483850","exchange":"KS","type":"etf","market":"KR"},
  {"name":"TIGER 미국나스닥100커버드콜ATM","ticker":"495000","exchange":"KS","type":"etf","market":"KR"},
  {"name":"HANARO 고배당","ticker":"315400","exchange":"KS","type":"etf","market":"KR"},
  {"name":"SOL 미국배당다우존스","ticker":"446720","exchange":"KS","type":"etf","market":"KR"},
  {"name":"ACE 미국배당다우존스","ticker":"479850","exchange":"KS","type":"etf","market":"KR"},
  {"name":"ACE 미국배당성장나스닥","ticker":"461580","exchange":"KS","type":"etf","market":"KR"},
  {"name":"TIGER 200커버드콜5%OTM","ticker":"441640","exchange":"KS","type":"etf","market":"KR"},
  {"name":"ARIRANG 고배당주채권혼합","ticker":"161510","exchange":"KS","type":"etf","market":"KR"},
  {"name":"KODEX 코스닥150","ticker":"251340","exchange":"KS","type":"etf","market":"KR"},
  {"name":"TIGER 코스닥150","ticker":"168580","exchange":"KS","type":"etf","market":"KR"},
  {"name":"KODEX 선진국MSCI World","ticker":"133690","exchange":"KS","type":"etf","market":"KR"},
  {"name":"TIGER 해외선진국MSCI World","ticker":"195930","exchange":"KS","type":"etf","market":"KR"},
  {"name":"TIGER 단기채권액티브","ticker":"130680","exchange":"KS","type":"etf","market":"KR"},
  {"name":"TIGER 200IT","ticker":"305720","exchange":"KS","type":"etf","market":"KR"},
  {"name":"TIGER 200커버드콜ATM","ticker":"243880","exchange":"KS","type":"etf","market":"KR"},
  {"name":"KBSTAR 미국S&P500","ticker":"426800","exchange":"KS","type":"etf","market":"KR"},
  {"name":"KBSTAR 200","ticker":"287310","exchange":"KS","type":"etf","market":"KR"},
  {"name":"TIGER 글로벌멀티에셋TIF액티브","ticker":"364980","exchange":"KS","type":"etf","market":"KR"},
  {"name":"TIGER 미국배당+7%프리미엄S&P500","ticker":"498470","exchange":"KS","type":"etf","market":"KR"},
  {"name":"TIGER 미국배당+10%프리미엄다우존스(H)","ticker":"487290","exchange":"KS","type":"etf","market":"KR"},
  {"name":"SOL 미국배당다우존스(H)","ticker":"494670","exchange":"KS","type":"etf","market":"KR"},
  {"name":"ACE 미국고배당S&P배당귀족(합성H)","ticker":"495630","exchange":"KS","type":"etf","market":"KR"},
  {"name":"KODEX 미국30년국채+12%프리미엄","ticker":"451450","exchange":"KS","type":"etf","market":"KR"},
  {"name":"TIGER 200에너지화학","ticker":"396520","exchange":"KS","type":"etf","market":"KR"},
  {"name":"KODEX KRX300","ticker":"364970","exchange":"KS","type":"etf","market":"KR"},
  {"name":"KOSEF 고배당","ticker":"084010","exchange":"KS","type":"etf","market":"KR"},
  {"name":"KBSTAR 200고배당커버드콜ATM","ticker":"290080","exchange":"KS","type":"etf","market":"KR"},
  {"name":"이지스켄달스퀘어리츠","ticker":"365550","exchange":"KS","type":"reit","market":"KR"},
  {"name":"미래에셋글로벌리츠","ticker":"396690","exchange":"KS","type":"reit","market":"KR"},
  {"name":"제이알글로벌리츠","ticker":"348950","exchange":"KS","type":"reit","market":"KR"},
  {"name":"이지스레지던스리츠","ticker":"370090","exchange":"KS","type":"reit","market":"KR"},
  {"name":"코람코더원리츠","ticker":"417310","exchange":"KS","type":"reit","market":"KR"},
  {"name":"코람코에너지리츠","ticker":"350520","exchange":"KS","type":"reit","market":"KR"},
  {"name":"삼성FN리츠","ticker":"475560","exchange":"KS","type":"reit","market":"KR"},
  {"name":"마스턴프리미어리츠","ticker":"466920","exchange":"KS","type":"reit","market":"KR"},
  {"name":"이리츠코크렙","ticker":"350360","exchange":"KS","type":"reit","market":"KR"},
  {"name":"NH올원리츠","ticker":"323250","exchange":"KS","type":"reit","market":"KR"},
  {"name":"하나대체투자리츠","ticker":"396420","exchange":"KS","type":"reit","market":"KR"},
  {"name":"와이엔텍","ticker":"072130","exchange":"KQ","type":"stock","market":"KR"},
  {"name":"고려아연","ticker":"010130","exchange":"KS","type":"stock","market":"KR"},
  {"name":"LG화학","ticker":"051910","exchange":"KS","type":"stock","market":"KR"},
  {"name":"현대모비스","ticker":"012330","exchange":"KS","type":"stock","market":"KR"},
  {"name":"삼성물산","ticker":"028260","exchange":"KS","type":"stock","market":"KR"},
  {"name":"LG전자","ticker":"066570","exchange":"KS","type":"stock","market":"KR"},
  {"name":"기아","ticker":"000270","exchange":"KS","type":"stock","market":"KR"},
  {"name":"현대차","ticker":"005380","exchange":"KS","type":"stock","market":"KR"},
  {"name":"NAVER","ticker":"035420","exchange":"KS","type":"stock","market":"KR"},
  {"name":"카카오","ticker":"035720","exchange":"KS","type":"stock","market":"KR"},
  {"name":"셀트리온","ticker":"068270","exchange":"KS","type":"stock","market":"KR"},
  {"name":"SK이노베이션","ticker":"096770","exchange":"KS","type":"stock","market":"KR"},
  {"name":"한국전력","ticker":"015760","exchange":"KS","type":"stock","market":"KR"},
  {"name":"우리금융지주","ticker":"316140","exchange":"KS","type":"stock","market":"KR"},
  {"name":"메리츠금융지주","ticker":"138040","exchange":"KS","type":"stock","market":"KR"},
  {"name":"BNK금융지주","ticker":"138930","exchange":"KS","type":"stock","market":"KR"},
  {"name":"DGB금융지주","ticker":"139130","exchange":"KS","type":"stock","market":"KR"},
  {"name":"JB금융지주","ticker":"175330","exchange":"KS","type":"stock","market":"KR"},
  {"name":"삼성생명","ticker":"032830","exchange":"KS","type":"stock","market":"KR"},
  {"name":"한화생명","ticker":"088350","exchange":"KS","type":"stock","market":"KR"},
  {"name":"삼성화재","ticker":"000810","exchange":"KS","type":"stock","market":"KR"},
  {"name":"현대해상","ticker":"001450","exchange":"KS","type":"stock","market":"KR"},
  {"name":"GS건설","ticker":"006360","exchange":"KS","type":"stock","market":"KR"},
  {"name":"DL이앤씨","ticker":"375500","exchange":"KS","type":"stock","market":"KR"},
  {"name":"현대건설","ticker":"000720","exchange":"KS","type":"stock","market":"KR"},
  {"name":"SK텔레콤","ticker":"017670","exchange":"KS","type":"stock","market":"KR"},
  {"name":"KT","ticker":"030200","exchange":"KS","type":"stock","market":"KR"},
  {"name":"LG유플러스","ticker":"032640","exchange":"KS","type":"stock","market":"KR"},
  {"name":"코웨이","ticker":"021240","exchange":"KS","type":"stock","market":"KR"},
  {"name":"BGF리테일","ticker":"282330","exchange":"KS","type":"stock","market":"KR"},
  {"name":"GS리테일","ticker":"007070","exchange":"KS","type":"stock","market":"KR"},
  {"name":"이마트","ticker":"139480","exchange":"KS","type":"stock","market":"KR"},
  {"name":"롯데쇼핑","ticker":"023530","exchange":"KS","type":"stock","market":"KR"},
  {"name":"CJ제일제당","ticker":"097950","exchange":"KS","type":"stock","market":"KR"},
  {"name":"오리온","ticker":"271560","exchange":"KS","type":"stock","market":"KR"},
  {"name":"농심","ticker":"004370","exchange":"KS","type":"stock","market":"KR"},
  {"name":"하이트진로","ticker":"000080","exchange":"KS","type":"stock","market":"KR"},
  {"name":"OB맥주(오비맥주)","ticker":"005180","exchange":"KS","type":"stock","market":"KR"},
  {"name":"한미약품","ticker":"128940","exchange":"KS","type":"stock","market":"KR"},
  {"name":"유한양행","ticker":"000100","exchange":"KS","type":"stock","market":"KR"},
  {"name":"GKL","ticker":"114090","exchange":"KS","type":"stock","market":"KR"},
  {"name":"강원랜드","ticker":"035250","exchange":"KS","type":"stock","market":"KR"},
  {"name":"한국가스공사","ticker":"036460","exchange":"KS","type":"stock","market":"KR"},
  {"name":"한국지역난방공사","ticker":"071320","exchange":"KS","type":"stock","market":"KR"}
]
